{
  "id": "getting-started/first-stake",
  "title": "Your First Stake",
  "description": "This guide will walk you through making your first stake on UrStake. We'll cover both APT and USDC staking options.",
  "source": "@site/docs/getting-started/first-stake.md",
  "sourceDirName": "getting-started",
  "slug": "/getting-started/first-stake",
  "permalink": "/getting-started/first-stake",
  "draft": false,
  "unlisted": false,
  "editUrl": "https://github.com/alade-dev/urstake/tree/main/docs/docs/getting-started/first-stake.md",
  "tags": [],
  "version": "current",
  "sidebarPosition": 3,
  "frontMatter": {
    "sidebar_position": 3
  },
  "sidebar": "tutorialSidebar",
  "previous": {
    "title": "Wallet Setup",
    "permalink": "/getting-started/wallet-setup"
  },
  "next": {
    "title": "APT Staking Guide",
    "permalink": "/user-guide/staking-apt"
  }
}